bru_analysis/common/extract_account_ids_fb.py
bru_analysis/common/find_text.py
bru_analysis/common/general_utils.py
bru_analysis/common/groups.py
bru_analysis/common/identify_social_network.py
bru_analysis/common/metric_transformation.py
bru_analysis/common/nlp_utils.py
bru_analysis/common/stopwords/English.txt
bru_analysis/common/stopwords/Spanish.txt
bru_analysis/engagement_rate.py
bru_analysis/ft_test/test_effective_content.py
bru_analysis/ft_test/test_emotion.py
bru_analysis/ft_test/test_extract_ids.py
bru_analysis/ft_test/test_find_text.py
bru_analysis/ft_test/test_groups.py
bru_analysis/ft_test/test_pqrs.py
bru_analysis/ft_test/test_sttm.py
bru_analysis/most_effective_content.py
bru_analysis/pqrs.py
bru_analysis/sentiment_emotion.py
bru_analysis/sttm_groups.py
bru_analysis/unit_test/ut_effective_content.py
bru_analysis/unit_test/ut_groups_fb.py
bru_analysis/unit_test/ut_groups_ig.py
bru_analysis/unit_test/ut_groups_tw.py
bru_analysis/unit_test/ut_pqrs.py
bru_analysis/unit_test/ut_sentiment_emotion.py
bru_analysis/unit_test/ut_sttm_groups.py
bru_analysis-0.5.3.dist-info/LICENSE
bru_analysis-0.5.3.dist-info/METADATA
bru_analysis-0.5.3.dist-info/WHEEL
bru_analysis-0.5.3.dist-info/RECORD
